odoo/addons/subbeticaecologica/__init__.py
odoo/addons/subbeticaecologica/__manifest__.py
odoo/addons/subbeticaecologica/i18n/es.po
odoo/addons/subbeticaecologica/report/__init__.py
odoo/addons/subbeticaecologica/report/sale_report.py
odoo14_addon_subbeticaecologica-14.0.0.0.1.dist-info/METADATA
odoo14_addon_subbeticaecologica-14.0.0.0.1.dist-info/WHEEL
odoo14_addon_subbeticaecologica-14.0.0.0.1.dist-info/top_level.txt
odoo14_addon_subbeticaecologica-14.0.0.0.1.dist-info/RECORD
